<?xml version="1.0" encoding="UTF-8"?>
<!DOCTYPE mapper PUBLIC "-//mybatis.org//DTD Mapper 3.0//EN" "http://mybatis.org/dtd/mybatis-3-mapper.dtd">
<mapper namespace="com.bryllyant.kona.app.dao.ProductSkuMapper">
  <resultMap id="BaseResultMap" type="com.bryllyant.kona.app.entity.ProductSku">
    <!--
      WARNING - @mbg.generated
      This element is automatically generated by MyBatis Generator, do not modify.
      This element was generated on Sat May 12 06:10:33 EDT 2018.
    -->
    <id column="id" jdbcType="BIGINT" property="id" />
    <result column="uid" jdbcType="VARCHAR" property="uid" />
    <result column="product_id" jdbcType="BIGINT" property="productId" />
    <result column="name" jdbcType="VARCHAR" property="name" />
    <result column="sku" jdbcType="VARCHAR" property="sku" />
    <result column="variants" jdbcType="VARCHAR" property="variants" typeHandler="com.bryllyant.kona.data.mybatis.KMapHandler" />
    <result column="description" jdbcType="VARCHAR" property="description" />
    <result column="display_order" jdbcType="INTEGER" property="displayOrder" />
    <result column="price" jdbcType="DECIMAL" property="price" />
    <result column="setup_fee" jdbcType="DECIMAL" property="setupFee" />
    <result column="trial_days" jdbcType="INTEGER" property="trialDays" />
    <result column="subscription" jdbcType="BIT" property="subscription" />
    <result column="subscription_days" jdbcType="INTEGER" property="subscriptionDays" />
    <result column="enabled" jdbcType="BIT" property="enabled" />
    <result column="created_date" jdbcType="TIMESTAMP" property="createdDate" />
    <result column="updated_date" jdbcType="TIMESTAMP" property="updatedDate" />
  </resultMap>
  <sql id="Example_Where_Clause">
    <!--
      WARNING - @mbg.generated
      This element is automatically generated by MyBatis Generator, do not modify.
      This element was generated on Sat May 12 06:10:33 EDT 2018.
    -->
    <where>
      <foreach collection="oredCriteria" item="criteria" separator="or">
        <if test="criteria.valid">
          <trim prefix="(" prefixOverrides="and" suffix=")">
            <foreach collection="criteria.criteria" item="criterion">
              <choose>
                <when test="criterion.noValue">
                  and ${criterion.condition}
                </when>
                <when test="criterion.singleValue">
                  and ${criterion.condition} #{criterion.value}
                </when>
                <when test="criterion.betweenValue">
                  and ${criterion.condition} #{criterion.value} and #{criterion.secondValue}
                </when>
                <when test="criterion.listValue">
                  and ${criterion.condition}
                  <foreach close=")" collection="criterion.value" item="listItem" open="(" separator=",">
                    #{listItem}
                  </foreach>
                </when>
              </choose>
            </foreach>
            <foreach collection="criteria.variantsCriteria" item="criterion">
              <choose>
                <when test="criterion.noValue">
                  and ${criterion.condition}
                </when>
                <when test="criterion.singleValue">
                  and ${criterion.condition} #{criterion.value,typeHandler=com.bryllyant.kona.data.mybatis.KMapHandler}
                </when>
                <when test="criterion.betweenValue">
                  and ${criterion.condition} #{criterion.value,typeHandler=com.bryllyant.kona.data.mybatis.KMapHandler} and #{criterion.secondValue,typeHandler=com.bryllyant.kona.data.mybatis.KMapHandler}
                </when>
                <when test="criterion.listValue">
                  and ${criterion.condition}
                  <foreach close=")" collection="criterion.value" item="listItem" open="(" separator=",">
                    #{listItem,typeHandler=com.bryllyant.kona.data.mybatis.KMapHandler}
                  </foreach>
                </when>
              </choose>
            </foreach>
          </trim>
        </if>
      </foreach>
      <if test="fts != null">
        AND MATCH (`uid`,`name`,`sku`,`variants`,`description`) AGAINST ('${fts}' IN BOOLEAN MODE)
      </if>
    </where>
  </sql>
  <sql id="Update_By_Example_Where_Clause">
    <!--
      WARNING - @mbg.generated
      This element is automatically generated by MyBatis Generator, do not modify.
      This element was generated on Sat May 12 06:10:33 EDT 2018.
    -->
    <where>
      <foreach collection="example.oredCriteria" item="criteria" separator="or">
        <if test="criteria.valid">
          <trim prefix="(" prefixOverrides="and" suffix=")">
            <foreach collection="criteria.criteria" item="criterion">
              <choose>
                <when test="criterion.noValue">
                  and ${criterion.condition}
                </when>
                <when test="criterion.singleValue">
                  and ${criterion.condition} #{criterion.value}
                </when>
                <when test="criterion.betweenValue">
                  and ${criterion.condition} #{criterion.value} and #{criterion.secondValue}
                </when>
                <when test="criterion.listValue">
                  and ${criterion.condition}
                  <foreach close=")" collection="criterion.value" item="listItem" open="(" separator=",">
                    #{listItem}
                  </foreach>
                </when>
              </choose>
            </foreach>
            <foreach collection="criteria.variantsCriteria" item="criterion">
              <choose>
                <when test="criterion.noValue">
                  and ${criterion.condition}
                </when>
                <when test="criterion.singleValue">
                  and ${criterion.condition} #{criterion.value,typeHandler=com.bryllyant.kona.data.mybatis.KMapHandler}
                </when>
                <when test="criterion.betweenValue">
                  and ${criterion.condition} #{criterion.value,typeHandler=com.bryllyant.kona.data.mybatis.KMapHandler} and #{criterion.secondValue,typeHandler=com.bryllyant.kona.data.mybatis.KMapHandler}
                </when>
                <when test="criterion.listValue">
                  and ${criterion.condition}
                  <foreach close=")" collection="criterion.value" item="listItem" open="(" separator=",">
                    #{listItem,typeHandler=com.bryllyant.kona.data.mybatis.KMapHandler}
                  </foreach>
                </when>
              </choose>
            </foreach>
          </trim>
        </if>
      </foreach>
      <if test="fts != null">
        AND MATCH (`uid`,`name`,`sku`,`variants`,`description`) AGAINST ('${fts}' IN BOOLEAN MODE)
      </if>
    </where>
  </sql>
  <sql id="Base_Column_List">
    <!--
      WARNING - @mbg.generated
      This element is automatically generated by MyBatis Generator, do not modify.
      This element was generated on Sat May 12 06:10:33 EDT 2018.
    -->
    `id`, `uid`, `product_id`, `name`, `sku`, `variants`, `description`, `display_order`, 
    `price`, `setup_fee`, `trial_days`, `subscription`, `subscription_days`, `enabled`, 
    `created_date`, `updated_date`
  </sql>
  <select id="selectByExample" parameterType="com.bryllyant.kona.app.entity.ProductSkuExample" resultMap="BaseResultMap">
    <!--
      WARNING - @mbg.generated
      This element is automatically generated by MyBatis Generator, do not modify.
      This element was generated on Sat May 12 06:10:33 EDT 2018.
    -->
    select
    <if test="distinct">
      distinct
    </if>
    <include refid="Base_Column_List" />
    from `kona__product_sku`
    <if test="_parameter != null">
      <include refid="Example_Where_Clause" />
    </if>
    <if test="orderByClause != null">
      order by ${orderByClause}
    </if>
    <if test="limit != null">
      limit ${limit}
    </if>
    <if test="offset != null">
      offset ${offset}
    </if>
  </select>
  <select id="selectByPrimaryKey" parameterType="java.lang.Long" resultMap="BaseResultMap">
    <!--
      WARNING - @mbg.generated
      This element is automatically generated by MyBatis Generator, do not modify.
      This element was generated on Sat May 12 06:10:33 EDT 2018.
    -->
    select 
    <include refid="Base_Column_List" />
    from `kona__product_sku`
    where `id` = #{id,jdbcType=BIGINT}
  </select>
  <delete id="deleteByPrimaryKey" parameterType="java.lang.Long">
    <!--
      WARNING - @mbg.generated
      This element is automatically generated by MyBatis Generator, do not modify.
      This element was generated on Sat May 12 06:10:33 EDT 2018.
    -->
    delete from `kona__product_sku`
    where `id` = #{id,jdbcType=BIGINT}
  </delete>
  <delete id="deleteByExample" parameterType="com.bryllyant.kona.app.entity.ProductSkuExample">
    <!--
      WARNING - @mbg.generated
      This element is automatically generated by MyBatis Generator, do not modify.
      This element was generated on Sat May 12 06:10:33 EDT 2018.
    -->
    delete from `kona__product_sku`
    <if test="_parameter != null">
      <include refid="Example_Where_Clause" />
    </if>
  </delete>
  <insert id="insert" parameterType="com.bryllyant.kona.app.entity.ProductSku">
    <!--
      WARNING - @mbg.generated
      This element is automatically generated by MyBatis Generator, do not modify.
      This element was generated on Sat May 12 06:10:33 EDT 2018.
    -->
    <selectKey keyProperty="id" order="AFTER" resultType="java.lang.Long">
      SELECT LAST_INSERT_ID()
    </selectKey>
    insert into `kona__product_sku` (`uid`, `product_id`, `name`, 
      `sku`, `variants`, 
      `description`, `display_order`, `price`, 
      `setup_fee`, `trial_days`, `subscription`, 
      `subscription_days`, `enabled`, `created_date`, 
      `updated_date`)
    values (#{uid,jdbcType=VARCHAR}, #{productId,jdbcType=BIGINT}, #{name,jdbcType=VARCHAR}, 
      #{sku,jdbcType=VARCHAR}, #{variants,jdbcType=VARCHAR,typeHandler=com.bryllyant.kona.data.mybatis.KMapHandler}, 
      #{description,jdbcType=VARCHAR}, #{displayOrder,jdbcType=INTEGER}, #{price,jdbcType=DECIMAL}, 
      #{setupFee,jdbcType=DECIMAL}, #{trialDays,jdbcType=INTEGER}, #{subscription,jdbcType=BIT}, 
      #{subscriptionDays,jdbcType=INTEGER}, #{enabled,jdbcType=BIT}, #{createdDate,jdbcType=TIMESTAMP}, 
      #{updatedDate,jdbcType=TIMESTAMP})
  </insert>
  <insert id="insertSelective" parameterType="com.bryllyant.kona.app.entity.ProductSku">
    <!--
      WARNING - @mbg.generated
      This element is automatically generated by MyBatis Generator, do not modify.
      This element was generated on Sat May 12 06:10:33 EDT 2018.
    -->
    <selectKey keyProperty="id" order="AFTER" resultType="java.lang.Long">
      SELECT LAST_INSERT_ID()
    </selectKey>
    insert into `kona__product_sku`
    <trim prefix="(" suffix=")" suffixOverrides=",">
      <if test="uid != null">
        `uid`,
      </if>
      <if test="productId != null">
        `product_id`,
      </if>
      <if test="name != null">
        `name`,
      </if>
      <if test="sku != null">
        `sku`,
      </if>
      <if test="variants != null">
        `variants`,
      </if>
      <if test="description != null">
        `description`,
      </if>
      <if test="displayOrder != null">
        `display_order`,
      </if>
      <if test="price != null">
        `price`,
      </if>
      <if test="setupFee != null">
        `setup_fee`,
      </if>
      <if test="trialDays != null">
        `trial_days`,
      </if>
      `subscription`,
      <if test="subscriptionDays != null">
        `subscription_days`,
      </if>
      `enabled`,
      <if test="createdDate != null">
        `created_date`,
      </if>
      <if test="updatedDate != null">
        `updated_date`,
      </if>
    </trim>
    <trim prefix="values (" suffix=")" suffixOverrides=",">
      <if test="uid != null">
        #{uid,jdbcType=VARCHAR},
      </if>
      <if test="productId != null">
        #{productId,jdbcType=BIGINT},
      </if>
      <if test="name != null">
        #{name,jdbcType=VARCHAR},
      </if>
      <if test="sku != null">
        #{sku,jdbcType=VARCHAR},
      </if>
      <if test="variants != null">
        #{variants,jdbcType=VARCHAR,typeHandler=com.bryllyant.kona.data.mybatis.KMapHandler},
      </if>
      <if test="description != null">
        #{description,jdbcType=VARCHAR},
      </if>
      <if test="displayOrder != null">
        #{displayOrder,jdbcType=INTEGER},
      </if>
      <if test="price != null">
        #{price,jdbcType=DECIMAL},
      </if>
      <if test="setupFee != null">
        #{setupFee,jdbcType=DECIMAL},
      </if>
      <if test="trialDays != null">
        #{trialDays,jdbcType=INTEGER},
      </if>
      #{subscription,jdbcType=BIT},
      <if test="subscriptionDays != null">
        #{subscriptionDays,jdbcType=INTEGER},
      </if>
      #{enabled,jdbcType=BIT},
      <if test="createdDate != null">
        #{createdDate,jdbcType=TIMESTAMP},
      </if>
      <if test="updatedDate != null">
        #{updatedDate,jdbcType=TIMESTAMP},
      </if>
    </trim>
  </insert>
  <select id="countByExample" parameterType="com.bryllyant.kona.app.entity.ProductSkuExample" resultType="java.lang.Long">
    <!--
      WARNING - @mbg.generated
      This element is automatically generated by MyBatis Generator, do not modify.
      This element was generated on Sat May 12 06:10:33 EDT 2018.
    -->
    select count(*) from `kona__product_sku`
    <if test="_parameter != null">
      <include refid="Example_Where_Clause" />
    </if>
  </select>
  <update id="updateByExampleSelective" parameterType="map">
    <!--
      WARNING - @mbg.generated
      This element is automatically generated by MyBatis Generator, do not modify.
      This element was generated on Sat May 12 06:10:33 EDT 2018.
    -->
    update `kona__product_sku`
    <set>
      <if test="record.id != null">
        `id` = #{record.id,jdbcType=BIGINT},
      </if>
      <if test="record.uid != null">
        `uid` = #{record.uid,jdbcType=VARCHAR},
      </if>
      <if test="record.productId != null">
        `product_id` = #{record.productId,jdbcType=BIGINT},
      </if>
      <if test="record.name != null">
        `name` = #{record.name,jdbcType=VARCHAR},
      </if>
      <if test="record.sku != null">
        `sku` = #{record.sku,jdbcType=VARCHAR},
      </if>
      <if test="record.variants != null">
        `variants` = #{record.variants,jdbcType=VARCHAR,typeHandler=com.bryllyant.kona.data.mybatis.KMapHandler},
      </if>
      <if test="record.description != null">
        `description` = #{record.description,jdbcType=VARCHAR},
      </if>
      <if test="record.displayOrder != null">
        `display_order` = #{record.displayOrder,jdbcType=INTEGER},
      </if>
      <if test="record.price != null">
        `price` = #{record.price,jdbcType=DECIMAL},
      </if>
      <if test="record.setupFee != null">
        `setup_fee` = #{record.setupFee,jdbcType=DECIMAL},
      </if>
      <if test="record.trialDays != null">
        `trial_days` = #{record.trialDays,jdbcType=INTEGER},
      </if>
      <if test="record.subscription != null">
        `subscription` = #{record.subscription,jdbcType=BIT},
      </if>
      <if test="record.subscriptionDays != null">
        `subscription_days` = #{record.subscriptionDays,jdbcType=INTEGER},
      </if>
      <if test="record.enabled != null">
        `enabled` = #{record.enabled,jdbcType=BIT},
      </if>
      <if test="record.createdDate != null">
        `created_date` = #{record.createdDate,jdbcType=TIMESTAMP},
      </if>
      <if test="record.updatedDate != null">
        `updated_date` = #{record.updatedDate,jdbcType=TIMESTAMP},
      </if>
    </set>
    <if test="_parameter != null">
      <include refid="Update_By_Example_Where_Clause" />
    </if>
  </update>
  <update id="updateByExample" parameterType="map">
    <!--
      WARNING - @mbg.generated
      This element is automatically generated by MyBatis Generator, do not modify.
      This element was generated on Sat May 12 06:10:33 EDT 2018.
    -->
    update `kona__product_sku`
    set `id` = #{record.id,jdbcType=BIGINT},
      `uid` = #{record.uid,jdbcType=VARCHAR},
      `product_id` = #{record.productId,jdbcType=BIGINT},
      `name` = #{record.name,jdbcType=VARCHAR},
      `sku` = #{record.sku,jdbcType=VARCHAR},
      `variants` = #{record.variants,jdbcType=VARCHAR,typeHandler=com.bryllyant.kona.data.mybatis.KMapHandler},
      `description` = #{record.description,jdbcType=VARCHAR},
      `display_order` = #{record.displayOrder,jdbcType=INTEGER},
      `price` = #{record.price,jdbcType=DECIMAL},
      `setup_fee` = #{record.setupFee,jdbcType=DECIMAL},
      `trial_days` = #{record.trialDays,jdbcType=INTEGER},
      `subscription` = #{record.subscription,jdbcType=BIT},
      `subscription_days` = #{record.subscriptionDays,jdbcType=INTEGER},
      `enabled` = #{record.enabled,jdbcType=BIT},
      `created_date` = #{record.createdDate,jdbcType=TIMESTAMP},
      `updated_date` = #{record.updatedDate,jdbcType=TIMESTAMP}
    <if test="_parameter != null">
      <include refid="Update_By_Example_Where_Clause" />
    </if>
  </update>
  <update id="updateByPrimaryKeySelective" parameterType="com.bryllyant.kona.app.entity.ProductSku">
    <!--
      WARNING - @mbg.generated
      This element is automatically generated by MyBatis Generator, do not modify.
      This element was generated on Sat May 12 06:10:33 EDT 2018.
    -->
    update `kona__product_sku`
    <set>
      <if test="uid != null">
        `uid` = #{uid,jdbcType=VARCHAR},
      </if>
      <if test="productId != null">
        `product_id` = #{productId,jdbcType=BIGINT},
      </if>
      <if test="name != null">
        `name` = #{name,jdbcType=VARCHAR},
      </if>
      <if test="sku != null">
        `sku` = #{sku,jdbcType=VARCHAR},
      </if>
      <if test="variants != null">
        `variants` = #{variants,jdbcType=VARCHAR,typeHandler=com.bryllyant.kona.data.mybatis.KMapHandler},
      </if>
      <if test="description != null">
        `description` = #{description,jdbcType=VARCHAR},
      </if>
      <if test="displayOrder != null">
        `display_order` = #{displayOrder,jdbcType=INTEGER},
      </if>
      <if test="price != null">
        `price` = #{price,jdbcType=DECIMAL},
      </if>
      <if test="setupFee != null">
        `setup_fee` = #{setupFee,jdbcType=DECIMAL},
      </if>
      <if test="trialDays != null">
        `trial_days` = #{trialDays,jdbcType=INTEGER},
      </if>
      <if test="subscription != null">
        `subscription` = #{subscription,jdbcType=BIT},
      </if>
      <if test="subscriptionDays != null">
        `subscription_days` = #{subscriptionDays,jdbcType=INTEGER},
      </if>
      <if test="enabled != null">
        `enabled` = #{enabled,jdbcType=BIT},
      </if>
      <if test="createdDate != null">
        `created_date` = #{createdDate,jdbcType=TIMESTAMP},
      </if>
      <if test="updatedDate != null">
        `updated_date` = #{updatedDate,jdbcType=TIMESTAMP},
      </if>
    </set>
    where `id` = #{id,jdbcType=BIGINT}
  </update>
  <update id="updateByPrimaryKey" parameterType="com.bryllyant.kona.app.entity.ProductSku">
    <!--
      WARNING - @mbg.generated
      This element is automatically generated by MyBatis Generator, do not modify.
      This element was generated on Sat May 12 06:10:33 EDT 2018.
    -->
    update `kona__product_sku`
    set `uid` = #{uid,jdbcType=VARCHAR},
      `product_id` = #{productId,jdbcType=BIGINT},
      `name` = #{name,jdbcType=VARCHAR},
      `sku` = #{sku,jdbcType=VARCHAR},
      `variants` = #{variants,jdbcType=VARCHAR,typeHandler=com.bryllyant.kona.data.mybatis.KMapHandler},
      `description` = #{description,jdbcType=VARCHAR},
      `display_order` = #{displayOrder,jdbcType=INTEGER},
      `price` = #{price,jdbcType=DECIMAL},
      `setup_fee` = #{setupFee,jdbcType=DECIMAL},
      `trial_days` = #{trialDays,jdbcType=INTEGER},
      `subscription` = #{subscription,jdbcType=BIT},
      `subscription_days` = #{subscriptionDays,jdbcType=INTEGER},
      `enabled` = #{enabled,jdbcType=BIT},
      `created_date` = #{createdDate,jdbcType=TIMESTAMP},
      `updated_date` = #{updatedDate,jdbcType=TIMESTAMP}
    where `id` = #{id,jdbcType=BIGINT}
  </update>
</mapper>